[
  {
    "time": "01:53 PM",
    "timestamp": 1765806828937,
    "teams": {
      "team_alpha": 0,
      "team_beta": 0,
      "team_gamma": 0
    },
    "total": 0
  },
  {
    "time": "02:12 PM",
    "timestamp": 1765807933023,
    "teams": {
      "team_alpha": 0,
      "team_beta": 0,
      "team_gamma": 0
    },
    "total": 0
  },
  {
    "time": "02:44 PM",
    "timestamp": 1765809872494,
    "teams": {
      "team_alpha": 0,
      "team_beta": 0,
      "team_gamma": 0
    },
    "total": 0
  },
  {
    "time": "02:59 PM",
    "timestamp": 1765810753530,
    "teams": {
      "team_alpha": 0,
      "team_beta": 0,
      "team_gamma": 0
    },
    "total": 0
  },
  {
    "time": "03:23 PM",
    "timestamp": 1765812218389,
    "teams": {
      "team_alpha": 0,
      "team_beta": 0,
      "team_gamma": 0
    },
    "total": 0
  },
  {
    "time": "03:44 PM",
    "timestamp": 1765813446696,
    "teams": {
      "team_alpha": 0,
      "team_beta": 0,
      "team_gamma": 0
    },
    "total": 0
  },
  {
    "time": "03:57 PM",
    "timestamp": 1765814244311,
    "teams": {
      "team_alpha": 0,
      "team_beta": 0,
      "team_gamma": 0
    },
    "total": 0
  },
  {
    "time": "04:22 PM",
    "timestamp": 1765815735160,
    "teams": {
      "team_alpha": 0,
      "team_beta": 0,
      "team_gamma": 0
    },
    "total": 0
  },
  {
    "time": "04:53 PM",
    "timestamp": 1765817601145,
    "teams": {
      "team_alpha": 0,
      "team_beta": 0,
      "team_gamma": 0
    },
    "total": 0
  },
  {
    "time": "05:14 PM",
    "timestamp": 1765818891281,
    "teams": {
      "team_alpha": 0,
      "team_beta": 0,
      "team_gamma": 0
    },
    "total": 0
  },
  {
    "time": "05:39 PM",
    "timestamp": 1765820348764,
    "teams": {
      "team_alpha": 0,
      "team_beta": 0,
      "team_gamma": 0
    },
    "total": 0
  },
  {
    "time": "05:52 PM",
    "timestamp": 1765821162798,
    "teams": {
      "team_alpha": 0,
      "team_beta": 0,
      "team_gamma": 0
    },
    "total": 0
  },
  {
    "time": "05:59 PM",
    "timestamp": 1765821545043,
    "teams": {
      "team_alpha": 0,
      "team_beta": 0,
      "team_gamma": 0
    },
    "total": 0
  },
  {
    "time": "06:30 PM",
    "timestamp": 1765823421237,
    "teams": {
      "team_alpha": 0,
      "team_beta": 0,
      "team_gamma": 0
    },
    "total": 0
  },
  {
    "time": "06:55 PM",
    "timestamp": 1765824905956,
    "teams": {
      "team_alpha": 0,
      "team_beta": 0,
      "team_gamma": 0
    },
    "total": 0
  },
  {
    "time": "07:11 PM",
    "timestamp": 1765825893549,
    "teams": {
      "team_alpha": 0,
      "team_beta": 0,
      "team_gamma": 0
    },
    "total": 0
  },
  {
    "time": "07:30 PM",
    "timestamp": 1765827000137,
    "teams": {
      "team_alpha": 0,
      "team_beta": 0,
      "team_gamma": 0
    },
    "total": 0
  },
  {
    "time": "07:40 PM",
    "timestamp": 1765827637309,
    "teams": {
      "team_alpha": 0,
      "team_beta": 0,
      "team_gamma": 0
    },
    "total": 0
  },
  {
    "time": "07:46 PM",
    "timestamp": 1765828018296,
    "teams": {
      "team_alpha": 0,
      "team_beta": 0,
      "team_gamma": 0
    },
    "total": 0
  },
  {
    "time": "07:53 PM",
    "timestamp": 1765828391108,
    "teams": {
      "team_alpha": 0,
      "team_beta": 0,
      "team_gamma": 0
    },
    "total": 0
  },
  {
    "time": "07:59 PM",
    "timestamp": 1765828742300,
    "teams": {
      "team_alpha": 0,
      "team_beta": 0,
      "team_gamma": 0
    },
    "total": 0
  },
  {
    "time": "08:22 PM",
    "timestamp": 1765830144185,
    "teams": {
      "team_alpha": 0,
      "team_beta": 0,
      "team_gamma": 0
    },
    "total": 0
  },
  {
    "time": "08:41 PM",
    "timestamp": 1765831304324,
    "teams": {
      "team_alpha": 0,
      "team_beta": 0,
      "team_gamma": 0
    },
    "total": 0
  },
  {
    "time": "08:53 PM",
    "timestamp": 1765832035194,
    "teams": {
      "team_alpha": 0,
      "team_beta": 0,
      "team_gamma": 0
    },
    "total": 0
  },
  {
    "time": "08:59 PM",
    "timestamp": 1765832375766,
    "teams": {
      "team_alpha": 0,
      "team_beta": 0,
      "team_gamma": 0
    },
    "total": 0
  },
  {
    "time": "09:19 PM",
    "timestamp": 1765833591371,
    "teams": {
      "team_alpha": 0,
      "team_beta": 0,
      "team_gamma": 0
    },
    "total": 0
  },
  {
    "time": "09:35 PM",
    "timestamp": 1765834521435,
    "teams": {
      "team_alpha": 0,
      "team_beta": 0,
      "team_gamma": 0
    },
    "total": 0
  },
  {
    "time": "09:45 PM",
    "timestamp": 1765835137503,
    "teams": {
      "team_alpha": 0,
      "team_beta": 0,
      "team_gamma": 0
    },
    "total": 0
  },
  {
    "time": "09:52 PM",
    "timestamp": 1765835523634,
    "teams": {
      "team_alpha": 0,
      "team_beta": 0,
      "team_gamma": 0
    },
    "total": 0
  },
  {
    "time": "09:58 PM",
    "timestamp": 1765835907795,
    "teams": {
      "team_alpha": 0,
      "team_beta": 0,
      "team_gamma": 0
    },
    "total": 0
  },
  {
    "time": "10:17 PM",
    "timestamp": 1765837050018,
    "teams": {
      "team_alpha": 0,
      "team_beta": 0,
      "team_gamma": 0
    },
    "total": 0
  },
  {
    "time": "10:37 PM",
    "timestamp": 1765838259228,
    "teams": {
      "team_alpha": 0,
      "team_beta": 0,
      "team_gamma": 0
    },
    "total": 0
  },
  {
    "time": "10:48 PM",
    "timestamp": 1765838939993,
    "teams": {
      "team_alpha": 0,
      "team_beta": 0,
      "team_gamma": 0
    },
    "total": 0
  },
  {
    "time": "10:54 PM",
    "timestamp": 1765839291486,
    "teams": {
      "team_alpha": 0,
      "team_beta": 0,
      "team_gamma": 0
    },
    "total": 0
  },
  {
    "time": "11:09 PM",
    "timestamp": 1765840175943,
    "teams": {
      "team_alpha": 0,
      "team_beta": 0,
      "team_gamma": 0
    },
    "total": 0
  },
  {
    "time": "11:30 PM",
    "timestamp": 1765841402113,
    "teams": {
      "team_alpha": 0,
      "team_beta": 0,
      "team_gamma": 0
    },
    "total": 0
  },
  {
    "time": "11:41 PM",
    "timestamp": 1765842080633,
    "teams": {
      "team_alpha": 0,
      "team_beta": 0,
      "team_gamma": 0
    },
    "total": 0
  },
  {
    "time": "11:48 PM",
    "timestamp": 1765842508713,
    "teams": {
      "team_alpha": 0,
      "team_beta": 0,
      "team_gamma": 0
    },
    "total": 0
  },
  {
    "time": "11:54 PM",
    "timestamp": 1765842863391,
    "teams": {
      "team_alpha": 0,
      "team_beta": 0,
      "team_gamma": 0
    },
    "total": 0
  },
  {
    "time": "12:00 AM",
    "timestamp": 1765843239916,
    "teams": {
      "team_alpha": 0,
      "team_beta": 0,
      "team_gamma": 0
    },
    "total": 0
  },
  {
    "time": "01:54 AM",
    "timestamp": 1765850041184,
    "teams": {
      "team_alpha": 0,
      "team_beta": 0,
      "team_gamma": 0
    },
    "total": 0
  },
  {
    "time": "03:15 AM",
    "timestamp": 1765854944876,
    "teams": {
      "team_alpha": 0,
      "team_beta": 0,
      "team_gamma": 0
    },
    "total": 0
  },
  {
    "time": "04:05 AM",
    "timestamp": 1765857905026,
    "teams": {
      "team_alpha": 0,
      "team_beta": 0,
      "team_gamma": 0
    },
    "total": 0
  },
  {
    "time": "04:41 AM",
    "timestamp": 1765860118043,
    "teams": {
      "team_alpha": 0,
      "team_beta": 0,
      "team_gamma": 0
    },
    "total": 0
  },
  {
    "time": "04:59 AM",
    "timestamp": 1765861160546,
    "teams": {
      "team_alpha": 0,
      "team_beta": 0,
      "team_gamma": 0
    },
    "total": 0
  },
  {
    "time": "05:21 AM",
    "timestamp": 1765862493795,
    "teams": {
      "team_alpha": 0,
      "team_beta": 0,
      "team_gamma": 0
    },
    "total": 0
  },
  {
    "time": "05:42 AM",
    "timestamp": 1765863733414,
    "teams": {
      "team_alpha": 0,
      "team_beta": 0,
      "team_gamma": 0
    },
    "total": 0
  },
  {
    "time": "05:52 AM",
    "timestamp": 1765864332693,
    "teams": {
      "team_alpha": 0,
      "team_beta": 0,
      "team_gamma": 0
    },
    "total": 0
  },
  {
    "time": "05:58 AM",
    "timestamp": 1765864690070,
    "teams": {
      "team_alpha": 0,
      "team_beta": 0,
      "team_gamma": 0
    },
    "total": 0
  },
  {
    "time": "06:27 AM",
    "timestamp": 1765866473487,
    "teams": {
      "team_alpha": 0,
      "team_beta": 0,
      "team_gamma": 0
    },
    "total": 0
  }
]