[
  {
    "time": "05:48 AM",
    "timestamp": 1768628899582,
    "teams": {
      "team_alpha": 0,
      "team_beta": 0,
      "team_gamma": 0
    },
    "total": 0
  },
  {
    "time": "05:54 AM",
    "timestamp": 1768629270445,
    "teams": {
      "team_alpha": 0,
      "team_beta": 0,
      "team_gamma": 0
    },
    "total": 0
  },
  {
    "time": "06:00 AM",
    "timestamp": 1768629630611,
    "teams": {
      "team_alpha": 0,
      "team_beta": 0,
      "team_gamma": 0
    },
    "total": 0
  },
  {
    "time": "06:34 AM",
    "timestamp": 1768631656901,
    "teams": {
      "team_alpha": 0,
      "team_beta": 0,
      "team_gamma": 0
    },
    "total": 0
  },
  {
    "time": "06:54 AM",
    "timestamp": 1768632876417,
    "teams": {
      "team_alpha": 0,
      "team_beta": 0,
      "team_gamma": 0
    },
    "total": 0
  },
  {
    "time": "07:09 AM",
    "timestamp": 1768633776174,
    "teams": {
      "team_alpha": 0,
      "team_beta": 0,
      "team_gamma": 0
    },
    "total": 0
  },
  {
    "time": "07:29 AM",
    "timestamp": 1768634951771,
    "teams": {
      "team_alpha": 0,
      "team_beta": 0,
      "team_gamma": 0
    },
    "total": 0
  },
  {
    "time": "07:39 AM",
    "timestamp": 1768635554193,
    "teams": {
      "team_alpha": 0,
      "team_beta": 0,
      "team_gamma": 0
    },
    "total": 0
  },
  {
    "time": "07:45 AM",
    "timestamp": 1768635936049,
    "teams": {
      "team_alpha": 0,
      "team_beta": 0,
      "team_gamma": 0
    },
    "total": 0
  },
  {
    "time": "07:51 AM",
    "timestamp": 1768636301974,
    "teams": {
      "team_alpha": 0,
      "team_beta": 0,
      "team_gamma": 0
    },
    "total": 0
  },
  {
    "time": "07:57 AM",
    "timestamp": 1768636652241,
    "teams": {
      "team_alpha": 0,
      "team_beta": 0,
      "team_gamma": 0
    },
    "total": 0
  },
  {
    "time": "08:20 AM",
    "timestamp": 1768638002099,
    "teams": {
      "team_alpha": 0,
      "team_beta": 0,
      "team_gamma": 0
    },
    "total": 0
  },
  {
    "time": "08:43 AM",
    "timestamp": 1768639394958,
    "teams": {
      "team_alpha": 0,
      "team_beta": 0,
      "team_gamma": 0
    },
    "total": 0
  },
  {
    "time": "08:55 AM",
    "timestamp": 1768640101688,
    "teams": {
      "team_alpha": 0,
      "team_beta": 0,
      "team_gamma": 0
    },
    "total": 0
  },
  {
    "time": "09:09 AM",
    "timestamp": 1768640995743,
    "teams": {
      "team_alpha": 0,
      "team_beta": 0,
      "team_gamma": 0
    },
    "total": 0
  },
  {
    "time": "09:31 AM",
    "timestamp": 1768642264085,
    "teams": {
      "team_alpha": 0,
      "team_beta": 0,
      "team_gamma": 0
    },
    "total": 0
  },
  {
    "time": "09:42 AM",
    "timestamp": 1768642941397,
    "teams": {
      "team_alpha": 0,
      "team_beta": 0,
      "team_gamma": 0
    },
    "total": 0
  },
  {
    "time": "09:49 AM",
    "timestamp": 1768643340177,
    "teams": {
      "team_alpha": 0,
      "team_beta": 0,
      "team_gamma": 0
    },
    "total": 0
  },
  {
    "time": "09:54 AM",
    "timestamp": 1768643690708,
    "teams": {
      "team_alpha": 0,
      "team_beta": 0,
      "team_gamma": 0
    },
    "total": 0
  },
  {
    "time": "10:08 AM",
    "timestamp": 1768644538790,
    "teams": {
      "team_alpha": 0,
      "team_beta": 0,
      "team_gamma": 0
    },
    "total": 0
  },
  {
    "time": "10:33 AM",
    "timestamp": 1768646031698,
    "teams": {
      "team_alpha": 0,
      "team_beta": 0,
      "team_gamma": 0
    },
    "total": 0
  },
  {
    "time": "10:46 AM",
    "timestamp": 1768646763164,
    "teams": {
      "team_alpha": 0,
      "team_beta": 0,
      "team_gamma": 0
    },
    "total": 0
  },
  {
    "time": "10:52 AM",
    "timestamp": 1768647162323,
    "teams": {
      "team_alpha": 0,
      "team_beta": 0,
      "team_gamma": 0
    },
    "total": 0
  },
  {
    "time": "10:58 AM",
    "timestamp": 1768647497820,
    "teams": {
      "team_alpha": 0,
      "team_beta": 0,
      "team_gamma": 0
    },
    "total": 0
  },
  {
    "time": "11:14 AM",
    "timestamp": 1768648471551,
    "teams": {
      "team_alpha": 0,
      "team_beta": 0,
      "team_gamma": 0
    },
    "total": 0
  },
  {
    "time": "11:28 AM",
    "timestamp": 1768649300076,
    "teams": {
      "team_alpha": 0,
      "team_beta": 0,
      "team_gamma": 0
    },
    "total": 0
  },
  {
    "time": "11:37 AM",
    "timestamp": 1768649847248,
    "teams": {
      "team_alpha": 0,
      "team_beta": 0,
      "team_gamma": 0
    },
    "total": 0
  },
  {
    "time": "11:44 AM",
    "timestamp": 1768650275164,
    "teams": {
      "team_alpha": 0,
      "team_beta": 0,
      "team_gamma": 0
    },
    "total": 0
  },
  {
    "time": "11:50 AM",
    "timestamp": 1768650628180,
    "teams": {
      "team_alpha": 0,
      "team_beta": 0,
      "team_gamma": 0
    },
    "total": 0
  },
  {
    "time": "11:56 AM",
    "timestamp": 1768650974016,
    "teams": {
      "team_alpha": 0,
      "team_beta": 0,
      "team_gamma": 0
    },
    "total": 0
  },
  {
    "time": "12:22 PM",
    "timestamp": 1768652547679,
    "teams": {
      "team_alpha": 0,
      "team_beta": 0,
      "team_gamma": 0
    },
    "total": 0
  },
  {
    "time": "01:02 PM",
    "timestamp": 1768654956439,
    "teams": {
      "team_alpha": 0,
      "team_beta": 0,
      "team_gamma": 0
    },
    "total": 0
  },
  {
    "time": "01:34 PM",
    "timestamp": 1768656851152,
    "teams": {
      "team_alpha": 0,
      "team_beta": 0,
      "team_gamma": 0
    },
    "total": 0
  },
  {
    "time": "01:46 PM",
    "timestamp": 1768657611689,
    "teams": {
      "team_alpha": 0,
      "team_beta": 0,
      "team_gamma": 0
    },
    "total": 0
  },
  {
    "time": "01:53 PM",
    "timestamp": 1768658011958,
    "teams": {
      "team_alpha": 0,
      "team_beta": 0,
      "team_gamma": 0
    },
    "total": 0
  },
  {
    "time": "01:59 PM",
    "timestamp": 1768658365460,
    "teams": {
      "team_alpha": 0,
      "team_beta": 0,
      "team_gamma": 0
    },
    "total": 0
  },
  {
    "time": "02:18 PM",
    "timestamp": 1768659514710,
    "teams": {
      "team_alpha": 0,
      "team_beta": 0,
      "team_gamma": 0
    },
    "total": 0
  },
  {
    "time": "02:36 PM",
    "timestamp": 1768660571268,
    "teams": {
      "team_alpha": 0,
      "team_beta": 0,
      "team_gamma": 0
    },
    "total": 0
  },
  {
    "time": "02:46 PM",
    "timestamp": 1768661212559,
    "teams": {
      "team_alpha": 0,
      "team_beta": 0,
      "team_gamma": 0
    },
    "total": 0
  },
  {
    "time": "02:53 PM",
    "timestamp": 1768661598426,
    "teams": {
      "team_alpha": 0,
      "team_beta": 0,
      "team_gamma": 0
    },
    "total": 0
  },
  {
    "time": "02:59 PM",
    "timestamp": 1768661960970,
    "teams": {
      "team_alpha": 0,
      "team_beta": 0,
      "team_gamma": 0
    },
    "total": 0
  },
  {
    "time": "03:19 PM",
    "timestamp": 1768663167966,
    "teams": {
      "team_alpha": 0,
      "team_beta": 0,
      "team_gamma": 0
    },
    "total": 0
  },
  {
    "time": "03:34 PM",
    "timestamp": 1768664076386,
    "teams": {
      "team_alpha": 0,
      "team_beta": 0,
      "team_gamma": 0
    },
    "total": 0
  },
  {
    "time": "03:44 PM",
    "timestamp": 1768664656066,
    "teams": {
      "team_alpha": 0,
      "team_beta": 0,
      "team_gamma": 0
    },
    "total": 0
  },
  {
    "time": "03:51 PM",
    "timestamp": 1768665070450,
    "teams": {
      "team_alpha": 0,
      "team_beta": 0,
      "team_gamma": 0
    },
    "total": 0
  },
  {
    "time": "03:56 PM",
    "timestamp": 1768665416867,
    "teams": {
      "team_alpha": 0,
      "team_beta": 0,
      "team_gamma": 0
    },
    "total": 0
  },
  {
    "time": "04:15 PM",
    "timestamp": 1768666550205,
    "teams": {
      "team_alpha": 0,
      "team_beta": 0,
      "team_gamma": 0
    },
    "total": 0
  },
  {
    "time": "04:38 PM",
    "timestamp": 1768667933628,
    "teams": {
      "team_alpha": 0,
      "team_beta": 0,
      "team_gamma": 0
    },
    "total": 0
  },
  {
    "time": "04:50 PM",
    "timestamp": 1768668653850,
    "teams": {
      "team_alpha": 0,
      "team_beta": 0,
      "team_gamma": 0
    },
    "total": 0
  },
  {
    "time": "04:57 PM",
    "timestamp": 1768669022838,
    "teams": {
      "team_alpha": 0,
      "team_beta": 0,
      "team_gamma": 0
    },
    "total": 0
  }
]