[
  {
    "time": "07:13 PM",
    "timestamp": 1768331596322,
    "teams": {
      "team_alpha": 0,
      "team_beta": 0,
      "team_gamma": 0
    },
    "total": 0
  },
  {
    "time": "07:30 PM",
    "timestamp": 1768332622589,
    "teams": {
      "team_alpha": 0,
      "team_beta": 0,
      "team_gamma": 0
    },
    "total": 0
  },
  {
    "time": "07:39 PM",
    "timestamp": 1768333178406,
    "teams": {
      "team_alpha": 0,
      "team_beta": 0,
      "team_gamma": 0
    },
    "total": 0
  },
  {
    "time": "07:45 PM",
    "timestamp": 1768333534081,
    "teams": {
      "team_alpha": 0,
      "team_beta": 0,
      "team_gamma": 0
    },
    "total": 0
  },
  {
    "time": "07:51 PM",
    "timestamp": 1768333919217,
    "teams": {
      "team_alpha": 0,
      "team_beta": 0,
      "team_gamma": 0
    },
    "total": 0
  },
  {
    "time": "07:58 PM",
    "timestamp": 1768334283901,
    "teams": {
      "team_alpha": 0,
      "team_beta": 0,
      "team_gamma": 0
    },
    "total": 0
  },
  {
    "time": "08:20 PM",
    "timestamp": 1768335630472,
    "teams": {
      "team_alpha": 0,
      "team_beta": 0,
      "team_gamma": 0
    },
    "total": 0
  },
  {
    "time": "08:42 PM",
    "timestamp": 1768336961046,
    "teams": {
      "team_alpha": 0,
      "team_beta": 0,
      "team_gamma": 0
    },
    "total": 0
  },
  {
    "time": "08:54 PM",
    "timestamp": 1768337694044,
    "teams": {
      "team_alpha": 0,
      "team_beta": 0,
      "team_gamma": 0
    },
    "total": 0
  },
  {
    "time": "09:09 PM",
    "timestamp": 1768338595259,
    "teams": {
      "team_alpha": 0,
      "team_beta": 0,
      "team_gamma": 0
    },
    "total": 0
  },
  {
    "time": "09:32 PM",
    "timestamp": 1768339959461,
    "teams": {
      "team_alpha": 0,
      "team_beta": 0,
      "team_gamma": 0
    },
    "total": 0
  },
  {
    "time": "09:45 PM",
    "timestamp": 1768340758570,
    "teams": {
      "team_alpha": 0,
      "team_beta": 0,
      "team_gamma": 0
    },
    "total": 0
  },
  {
    "time": "09:53 PM",
    "timestamp": 1768341219305,
    "teams": {
      "team_alpha": 0,
      "team_beta": 0,
      "team_gamma": 0
    },
    "total": 0
  },
  {
    "time": "09:59 PM",
    "timestamp": 1768341590197,
    "teams": {
      "team_alpha": 0,
      "team_beta": 0,
      "team_gamma": 0
    },
    "total": 0
  },
  {
    "time": "10:22 PM",
    "timestamp": 1768342958099,
    "teams": {
      "team_alpha": 0,
      "team_beta": 0,
      "team_gamma": 0
    },
    "total": 0
  },
  {
    "time": "10:42 PM",
    "timestamp": 1768344173059,
    "teams": {
      "team_alpha": 0,
      "team_beta": 0,
      "team_gamma": 0
    },
    "total": 0
  },
  {
    "time": "10:54 PM",
    "timestamp": 1768344889479,
    "teams": {
      "team_alpha": 0,
      "team_beta": 0,
      "team_gamma": 0
    },
    "total": 0
  },
  {
    "time": "11:09 PM",
    "timestamp": 1768345789509,
    "teams": {
      "team_alpha": 0,
      "team_beta": 0,
      "team_gamma": 0
    },
    "total": 0
  },
  {
    "time": "11:28 PM",
    "timestamp": 1768346898239,
    "teams": {
      "team_alpha": 0,
      "team_beta": 0,
      "team_gamma": 0
    },
    "total": 0
  },
  {
    "time": "11:38 PM",
    "timestamp": 1768347536516,
    "teams": {
      "team_alpha": 0,
      "team_beta": 0,
      "team_gamma": 0
    },
    "total": 0
  },
  {
    "time": "11:47 PM",
    "timestamp": 1768348066208,
    "teams": {
      "team_alpha": 0,
      "team_beta": 0,
      "team_gamma": 0
    },
    "total": 0
  },
  {
    "time": "11:53 PM",
    "timestamp": 1768348410938,
    "teams": {
      "team_alpha": 0,
      "team_beta": 0,
      "team_gamma": 0
    },
    "total": 0
  },
  {
    "time": "11:59 PM",
    "timestamp": 1768348781471,
    "teams": {
      "team_alpha": 0,
      "team_beta": 0,
      "team_gamma": 0
    },
    "total": 0
  },
  {
    "time": "01:51 AM",
    "timestamp": 1768355463152,
    "teams": {
      "team_alpha": 0,
      "team_beta": 0,
      "team_gamma": 0
    },
    "total": 0
  },
  {
    "time": "03:26 AM",
    "timestamp": 1768361219648,
    "teams": {
      "team_alpha": 0,
      "team_beta": 0,
      "team_gamma": 0
    },
    "total": 0
  },
  {
    "time": "04:31 AM",
    "timestamp": 1768365105878,
    "teams": {
      "team_alpha": 0,
      "team_beta": 0,
      "team_gamma": 0
    },
    "total": 0
  },
  {
    "time": "04:59 AM",
    "timestamp": 1768366777354,
    "teams": {
      "team_alpha": 0,
      "team_beta": 0,
      "team_gamma": 0
    },
    "total": 0
  },
  {
    "time": "05:24 AM",
    "timestamp": 1768368298931,
    "teams": {
      "team_alpha": 0,
      "team_beta": 0,
      "team_gamma": 0
    },
    "total": 0
  },
  {
    "time": "05:45 AM",
    "timestamp": 1768369512211,
    "teams": {
      "team_alpha": 0,
      "team_beta": 0,
      "team_gamma": 0
    },
    "total": 0
  },
  {
    "time": "05:55 AM",
    "timestamp": 1768370123869,
    "teams": {
      "team_alpha": 0,
      "team_beta": 0,
      "team_gamma": 0
    },
    "total": 0
  },
  {
    "time": "06:19 AM",
    "timestamp": 1768371596930,
    "teams": {
      "team_alpha": 0,
      "team_beta": 0,
      "team_gamma": 0
    },
    "total": 0
  },
  {
    "time": "06:52 AM",
    "timestamp": 1768373538423,
    "teams": {
      "team_alpha": 0,
      "team_beta": 0,
      "team_gamma": 0
    },
    "total": 0
  },
  {
    "time": "07:14 AM",
    "timestamp": 1768374880976,
    "teams": {
      "team_alpha": 0,
      "team_beta": 0,
      "team_gamma": 0
    },
    "total": 0
  },
  {
    "time": "07:37 AM",
    "timestamp": 1768376264409,
    "teams": {
      "team_alpha": 0,
      "team_beta": 0,
      "team_gamma": 0
    },
    "total": 0
  },
  {
    "time": "07:49 AM",
    "timestamp": 1768376999232,
    "teams": {
      "team_alpha": 0,
      "team_beta": 0,
      "team_gamma": 0
    },
    "total": 0
  },
  {
    "time": "07:56 AM",
    "timestamp": 1768377367826,
    "teams": {
      "team_alpha": 0,
      "team_beta": 0,
      "team_gamma": 0
    },
    "total": 0
  },
  {
    "time": "08:18 AM",
    "timestamp": 1768378718558,
    "teams": {
      "team_alpha": 0,
      "team_beta": 0,
      "team_gamma": 0
    },
    "total": 0
  },
  {
    "time": "08:53 AM",
    "timestamp": 1768380804755,
    "teams": {
      "team_alpha": 0,
      "team_beta": 0,
      "team_gamma": 0
    },
    "total": 0
  },
  {
    "time": "09:04 AM",
    "timestamp": 1768381447821,
    "teams": {
      "team_alpha": 0,
      "team_beta": 0,
      "team_gamma": 0
    },
    "total": 0
  },
  {
    "time": "09:37 AM",
    "timestamp": 1768383445782,
    "teams": {
      "team_alpha": 0,
      "team_beta": 0,
      "team_gamma": 0
    },
    "total": 0
  },
  {
    "time": "09:54 AM",
    "timestamp": 1768384446709,
    "teams": {
      "team_alpha": 0,
      "team_beta": 0,
      "team_gamma": 0
    },
    "total": 0
  },
  {
    "time": "10:00 AM",
    "timestamp": 1768384844260,
    "teams": {
      "team_alpha": 0,
      "team_beta": 0,
      "team_gamma": 0
    },
    "total": 0
  },
  {
    "time": "10:29 AM",
    "timestamp": 1768386576219,
    "teams": {
      "team_alpha": 0,
      "team_beta": 0,
      "team_gamma": 0
    },
    "total": 0
  },
  {
    "time": "10:51 AM",
    "timestamp": 1768387895274,
    "teams": {
      "team_alpha": 0,
      "team_beta": 0,
      "team_gamma": 0
    },
    "total": 0
  },
  {
    "time": "11:00 AM",
    "timestamp": 1768388447804,
    "teams": {
      "team_alpha": 0,
      "team_beta": 0,
      "team_gamma": 0
    },
    "total": 0
  },
  {
    "time": "11:25 AM",
    "timestamp": 1768389908868,
    "teams": {
      "team_alpha": 0,
      "team_beta": 0,
      "team_gamma": 0
    },
    "total": 0
  },
  {
    "time": "11:39 AM",
    "timestamp": 1768390792965,
    "teams": {
      "team_alpha": 0,
      "team_beta": 0,
      "team_gamma": 0
    },
    "total": 0
  },
  {
    "time": "11:49 AM",
    "timestamp": 1768391391318,
    "teams": {
      "team_alpha": 0,
      "team_beta": 0,
      "team_gamma": 0
    },
    "total": 0
  },
  {
    "time": "11:56 AM",
    "timestamp": 1768391763246,
    "teams": {
      "team_alpha": 0,
      "team_beta": 0,
      "team_gamma": 0
    },
    "total": 0
  },
  {
    "time": "12:26 PM",
    "timestamp": 1768393566953,
    "teams": {
      "team_alpha": 0,
      "team_beta": 0,
      "team_gamma": 0
    },
    "total": 0
  }
]