[
  {
    "time": "02:36 PM",
    "timestamp": 1764254180887,
    "teams": {
      "team_alpha": 0,
      "team_beta": 0,
      "team_gamma": 0
    },
    "total": 0
  },
  {
    "time": "02:48 PM",
    "timestamp": 1764254903534,
    "teams": {
      "team_alpha": 0,
      "team_beta": 0,
      "team_gamma": 0
    },
    "total": 0
  },
  {
    "time": "02:55 PM",
    "timestamp": 1764255319730,
    "teams": {
      "team_alpha": 0,
      "team_beta": 0,
      "team_gamma": 0
    },
    "total": 0
  },
  {
    "time": "03:10 PM",
    "timestamp": 1764256220757,
    "teams": {
      "team_alpha": 0,
      "team_beta": 0,
      "team_gamma": 0
    },
    "total": 0
  },
  {
    "time": "03:31 PM",
    "timestamp": 1764257491977,
    "teams": {
      "team_alpha": 0,
      "team_beta": 0,
      "team_gamma": 0
    },
    "total": 0
  },
  {
    "time": "03:43 PM",
    "timestamp": 1764258193714,
    "teams": {
      "team_alpha": 0,
      "team_beta": 0,
      "team_gamma": 0
    },
    "total": 0
  },
  {
    "time": "03:50 PM",
    "timestamp": 1764258625552,
    "teams": {
      "team_alpha": 0,
      "team_beta": 0,
      "team_gamma": 0
    },
    "total": 0
  },
  {
    "time": "03:56 PM",
    "timestamp": 1764259009422,
    "teams": {
      "team_alpha": 0,
      "team_beta": 0,
      "team_gamma": 0
    },
    "total": 0
  },
  {
    "time": "04:16 PM",
    "timestamp": 1764260201683,
    "teams": {
      "team_alpha": 0,
      "team_beta": 0,
      "team_gamma": 0
    },
    "total": 0
  },
  {
    "time": "04:42 PM",
    "timestamp": 1764261724490,
    "teams": {
      "team_alpha": 0,
      "team_beta": 0,
      "team_gamma": 0
    },
    "total": 0
  },
  {
    "time": "04:54 PM",
    "timestamp": 1764262453782,
    "teams": {
      "team_alpha": 0,
      "team_beta": 0,
      "team_gamma": 0
    },
    "total": 0
  },
  {
    "time": "05:00 PM",
    "timestamp": 1764262816004,
    "teams": {
      "team_alpha": 0,
      "team_beta": 0,
      "team_gamma": 0
    },
    "total": 0
  },
  {
    "time": "05:17 PM",
    "timestamp": 1764263872821,
    "teams": {
      "team_alpha": 0,
      "team_beta": 0,
      "team_gamma": 0
    },
    "total": 0
  },
  {
    "time": "05:31 PM",
    "timestamp": 1764264719679,
    "teams": {
      "team_alpha": 0,
      "team_beta": 0,
      "team_gamma": 0
    },
    "total": 0
  },
  {
    "time": "05:41 PM",
    "timestamp": 1764265298565,
    "teams": {
      "team_alpha": 0,
      "team_beta": 0,
      "team_gamma": 0
    },
    "total": 0
  },
  {
    "time": "05:47 PM",
    "timestamp": 1764265672716,
    "teams": {
      "team_alpha": 0,
      "team_beta": 0,
      "team_gamma": 0
    },
    "total": 0
  },
  {
    "time": "05:53 PM",
    "timestamp": 1764266034472,
    "teams": {
      "team_alpha": 0,
      "team_beta": 0,
      "team_gamma": 0
    },
    "total": 0
  },
  {
    "time": "05:59 PM",
    "timestamp": 1764266391382,
    "teams": {
      "team_alpha": 0,
      "team_beta": 0,
      "team_gamma": 0
    },
    "total": 0
  },
  {
    "time": "06:28 PM",
    "timestamp": 1764268130741,
    "teams": {
      "team_alpha": 0,
      "team_beta": 0,
      "team_gamma": 0
    },
    "total": 0
  },
  {
    "time": "06:48 PM",
    "timestamp": 1764269287762,
    "teams": {
      "team_alpha": 0,
      "team_beta": 0,
      "team_gamma": 0
    },
    "total": 0
  },
  {
    "time": "06:56 PM",
    "timestamp": 1764269763602,
    "teams": {
      "team_alpha": 0,
      "team_beta": 0,
      "team_gamma": 0
    },
    "total": 0
  },
  {
    "time": "07:09 PM",
    "timestamp": 1764270570451,
    "teams": {
      "team_alpha": 0,
      "team_beta": 0,
      "team_gamma": 0
    },
    "total": 0
  },
  {
    "time": "07:23 PM",
    "timestamp": 1764271394652,
    "teams": {
      "team_alpha": 0,
      "team_beta": 0,
      "team_gamma": 0
    },
    "total": 0
  },
  {
    "time": "07:29 PM",
    "timestamp": 1764271769742,
    "teams": {
      "team_alpha": 0,
      "team_beta": 0,
      "team_gamma": 0
    },
    "total": 0
  },
  {
    "time": "07:37 PM",
    "timestamp": 1764272225102,
    "teams": {
      "team_alpha": 0,
      "team_beta": 0,
      "team_gamma": 0
    },
    "total": 0
  },
  {
    "time": "07:42 PM",
    "timestamp": 1764272571915,
    "teams": {
      "team_alpha": 0,
      "team_beta": 0,
      "team_gamma": 0
    },
    "total": 0
  },
  {
    "time": "07:49 PM",
    "timestamp": 1764272949470,
    "teams": {
      "team_alpha": 0,
      "team_beta": 0,
      "team_gamma": 0
    },
    "total": 0
  },
  {
    "time": "07:54 PM",
    "timestamp": 1764273291412,
    "teams": {
      "team_alpha": 0,
      "team_beta": 0,
      "team_gamma": 0
    },
    "total": 0
  },
  {
    "time": "08:01 PM",
    "timestamp": 1764273703246,
    "teams": {
      "team_alpha": 0,
      "team_beta": 0,
      "team_gamma": 0
    },
    "total": 0
  },
  {
    "time": "08:25 PM",
    "timestamp": 1764275116896,
    "teams": {
      "team_alpha": 0,
      "team_beta": 0,
      "team_gamma": 0
    },
    "total": 0
  },
  {
    "time": "08:36 PM",
    "timestamp": 1764275815947,
    "teams": {
      "team_alpha": 0,
      "team_beta": 0,
      "team_gamma": 0
    },
    "total": 0
  },
  {
    "time": "08:44 PM",
    "timestamp": 1764276294094,
    "teams": {
      "team_alpha": 0,
      "team_beta": 0,
      "team_gamma": 0
    },
    "total": 0
  },
  {
    "time": "08:50 PM",
    "timestamp": 1764276644537,
    "teams": {
      "team_alpha": 0,
      "team_beta": 0,
      "team_gamma": 0
    },
    "total": 0
  },
  {
    "time": "08:56 PM",
    "timestamp": 1764277015718,
    "teams": {
      "team_alpha": 0,
      "team_beta": 0,
      "team_gamma": 0
    },
    "total": 0
  },
  {
    "time": "09:12 PM",
    "timestamp": 1764277932030,
    "teams": {
      "team_alpha": 0,
      "team_beta": 0,
      "team_gamma": 0
    },
    "total": 0
  },
  {
    "time": "09:27 PM",
    "timestamp": 1764278879958,
    "teams": {
      "team_alpha": 0,
      "team_beta": 0,
      "team_gamma": 0
    },
    "total": 0
  },
  {
    "time": "09:36 PM",
    "timestamp": 1764279380171,
    "teams": {
      "team_alpha": 0,
      "team_beta": 0,
      "team_gamma": 0
    },
    "total": 0
  },
  {
    "time": "09:42 PM",
    "timestamp": 1764279755282,
    "teams": {
      "team_alpha": 0,
      "team_beta": 0,
      "team_gamma": 0
    },
    "total": 0
  },
  {
    "time": "09:48 PM",
    "timestamp": 1764280133844,
    "teams": {
      "team_alpha": 0,
      "team_beta": 0,
      "team_gamma": 0
    },
    "total": 0
  },
  {
    "time": "09:55 PM",
    "timestamp": 1764280504554,
    "teams": {
      "team_alpha": 0,
      "team_beta": 0,
      "team_gamma": 0
    },
    "total": 0
  },
  {
    "time": "10:08 PM",
    "timestamp": 1764281337154,
    "teams": {
      "team_alpha": 0,
      "team_beta": 0,
      "team_gamma": 0
    },
    "total": 0
  },
  {
    "time": "10:30 PM",
    "timestamp": 1764282625198,
    "teams": {
      "team_alpha": 0,
      "team_beta": 0,
      "team_gamma": 0
    },
    "total": 0
  },
  {
    "time": "10:41 PM",
    "timestamp": 1764283291645,
    "teams": {
      "team_alpha": 0,
      "team_beta": 0,
      "team_gamma": 0
    },
    "total": 0
  },
  {
    "time": "10:47 PM",
    "timestamp": 1764283658640,
    "teams": {
      "team_alpha": 0,
      "team_beta": 0,
      "team_gamma": 0
    },
    "total": 0
  },
  {
    "time": "10:53 PM",
    "timestamp": 1764284014138,
    "teams": {
      "team_alpha": 0,
      "team_beta": 0,
      "team_gamma": 0
    },
    "total": 0
  },
  {
    "time": "10:59 PM",
    "timestamp": 1764284360170,
    "teams": {
      "team_alpha": 0,
      "team_beta": 0,
      "team_gamma": 0
    },
    "total": 0
  },
  {
    "time": "11:17 PM",
    "timestamp": 1764285474747,
    "teams": {
      "team_alpha": 0,
      "team_beta": 0,
      "team_gamma": 0
    },
    "total": 0
  },
  {
    "time": "11:30 PM",
    "timestamp": 1764286247257,
    "teams": {
      "team_alpha": 0,
      "team_beta": 0,
      "team_gamma": 0
    },
    "total": 0
  },
  {
    "time": "11:40 PM",
    "timestamp": 1764286804897,
    "teams": {
      "team_alpha": 0,
      "team_beta": 0,
      "team_gamma": 0
    },
    "total": 0
  },
  {
    "time": "11:45 PM",
    "timestamp": 1764287153834,
    "teams": {
      "team_alpha": 0,
      "team_beta": 0,
      "team_gamma": 0
    },
    "total": 0
  }
]