[
  {
    "time": "05:48 PM",
    "timestamp": 1766339287273,
    "teams": {
      "team_alpha": 0,
      "team_beta": 0,
      "team_gamma": 0
    },
    "total": 0
  },
  {
    "time": "05:54 PM",
    "timestamp": 1766339652859,
    "teams": {
      "team_alpha": 0,
      "team_beta": 0,
      "team_gamma": 0
    },
    "total": 0
  },
  {
    "time": "05:59 PM",
    "timestamp": 1766339990382,
    "teams": {
      "team_alpha": 0,
      "team_beta": 0,
      "team_gamma": 0
    },
    "total": 0
  },
  {
    "time": "06:28 PM",
    "timestamp": 1766341738187,
    "teams": {
      "team_alpha": 0,
      "team_beta": 0,
      "team_gamma": 0
    },
    "total": 0
  },
  {
    "time": "06:48 PM",
    "timestamp": 1766342916006,
    "teams": {
      "team_alpha": 0,
      "team_beta": 0,
      "team_gamma": 0
    },
    "total": 0
  },
  {
    "time": "06:57 PM",
    "timestamp": 1766343420748,
    "teams": {
      "team_alpha": 0,
      "team_beta": 0,
      "team_gamma": 0
    },
    "total": 0
  },
  {
    "time": "07:10 PM",
    "timestamp": 1766344244682,
    "teams": {
      "team_alpha": 0,
      "team_beta": 0,
      "team_gamma": 0
    },
    "total": 0
  },
  {
    "time": "07:24 PM",
    "timestamp": 1766345090398,
    "teams": {
      "team_alpha": 0,
      "team_beta": 0,
      "team_gamma": 0
    },
    "total": 0
  },
  {
    "time": "07:31 PM",
    "timestamp": 1766345461571,
    "teams": {
      "team_alpha": 0,
      "team_beta": 0,
      "team_gamma": 0
    },
    "total": 0
  },
  {
    "time": "07:38 PM",
    "timestamp": 1766345930363,
    "teams": {
      "team_alpha": 0,
      "team_beta": 0,
      "team_gamma": 0
    },
    "total": 0
  },
  {
    "time": "07:44 PM",
    "timestamp": 1766346282152,
    "teams": {
      "team_alpha": 0,
      "team_beta": 0,
      "team_gamma": 0
    },
    "total": 0
  },
  {
    "time": "07:50 PM",
    "timestamp": 1766346646703,
    "teams": {
      "team_alpha": 0,
      "team_beta": 0,
      "team_gamma": 0
    },
    "total": 0
  },
  {
    "time": "07:56 PM",
    "timestamp": 1766347011056,
    "teams": {
      "team_alpha": 0,
      "team_beta": 0,
      "team_gamma": 0
    },
    "total": 0
  },
  {
    "time": "08:14 PM",
    "timestamp": 1766348055146,
    "teams": {
      "team_alpha": 0,
      "team_beta": 0,
      "team_gamma": 0
    },
    "total": 0
  },
  {
    "time": "08:33 PM",
    "timestamp": 1766349197251,
    "teams": {
      "team_alpha": 0,
      "team_beta": 0,
      "team_gamma": 0
    },
    "total": 0
  },
  {
    "time": "08:44 PM",
    "timestamp": 1766349863445,
    "teams": {
      "team_alpha": 0,
      "team_beta": 0,
      "team_gamma": 0
    },
    "total": 0
  },
  {
    "time": "08:51 PM",
    "timestamp": 1766350270853,
    "teams": {
      "team_alpha": 0,
      "team_beta": 0,
      "team_gamma": 0
    },
    "total": 0
  },
  {
    "time": "08:57 PM",
    "timestamp": 1766350639354,
    "teams": {
      "team_alpha": 0,
      "team_beta": 0,
      "team_gamma": 0
    },
    "total": 0
  },
  {
    "time": "09:13 PM",
    "timestamp": 1766351594703,
    "teams": {
      "team_alpha": 0,
      "team_beta": 0,
      "team_gamma": 0
    },
    "total": 0
  },
  {
    "time": "09:28 PM",
    "timestamp": 1766352525383,
    "teams": {
      "team_alpha": 0,
      "team_beta": 0,
      "team_gamma": 0
    },
    "total": 0
  },
  {
    "time": "09:37 PM",
    "timestamp": 1766353078812,
    "teams": {
      "team_alpha": 0,
      "team_beta": 0,
      "team_gamma": 0
    },
    "total": 0
  },
  {
    "time": "09:44 PM",
    "timestamp": 1766353478962,
    "teams": {
      "team_alpha": 0,
      "team_beta": 0,
      "team_gamma": 0
    },
    "total": 0
  },
  {
    "time": "09:50 PM",
    "timestamp": 1766353840897,
    "teams": {
      "team_alpha": 0,
      "team_beta": 0,
      "team_gamma": 0
    },
    "total": 0
  },
  {
    "time": "09:56 PM",
    "timestamp": 1766354181757,
    "teams": {
      "team_alpha": 0,
      "team_beta": 0,
      "team_gamma": 0
    },
    "total": 0
  },
  {
    "time": "10:12 PM",
    "timestamp": 1766355124891,
    "teams": {
      "team_alpha": 0,
      "team_beta": 0,
      "team_gamma": 0
    },
    "total": 0
  },
  {
    "time": "10:32 PM",
    "timestamp": 1766356376935,
    "teams": {
      "team_alpha": 0,
      "team_beta": 0,
      "team_gamma": 0
    },
    "total": 0
  },
  {
    "time": "10:44 PM",
    "timestamp": 1766357076906,
    "teams": {
      "team_alpha": 0,
      "team_beta": 0,
      "team_gamma": 0
    },
    "total": 0
  },
  {
    "time": "10:50 PM",
    "timestamp": 1766357452868,
    "teams": {
      "team_alpha": 0,
      "team_beta": 0,
      "team_gamma": 0
    },
    "total": 0
  },
  {
    "time": "10:57 PM",
    "timestamp": 1766357823334,
    "teams": {
      "team_alpha": 0,
      "team_beta": 0,
      "team_gamma": 0
    },
    "total": 0
  },
  {
    "time": "11:13 PM",
    "timestamp": 1766358813333,
    "teams": {
      "team_alpha": 0,
      "team_beta": 0,
      "team_gamma": 0
    },
    "total": 0
  },
  {
    "time": "11:29 PM",
    "timestamp": 1766359797161,
    "teams": {
      "team_alpha": 0,
      "team_beta": 0,
      "team_gamma": 0
    },
    "total": 0
  },
  {
    "time": "11:40 PM",
    "timestamp": 1766360404605,
    "teams": {
      "team_alpha": 0,
      "team_beta": 0,
      "team_gamma": 0
    },
    "total": 0
  },
  {
    "time": "11:47 PM",
    "timestamp": 1766360832127,
    "teams": {
      "team_alpha": 0,
      "team_beta": 0,
      "team_gamma": 0
    },
    "total": 0
  },
  {
    "time": "11:53 PM",
    "timestamp": 1766361188913,
    "teams": {
      "team_alpha": 0,
      "team_beta": 0,
      "team_gamma": 0
    },
    "total": 0
  },
  {
    "time": "11:58 PM",
    "timestamp": 1766361525003,
    "teams": {
      "team_alpha": 0,
      "team_beta": 0,
      "team_gamma": 0
    },
    "total": 0
  },
  {
    "time": "01:39 AM",
    "timestamp": 1766367551589,
    "teams": {
      "team_alpha": 0,
      "team_beta": 0,
      "team_gamma": 0
    },
    "total": 0
  },
  {
    "time": "03:21 AM",
    "timestamp": 1766373673673,
    "teams": {
      "team_alpha": 0,
      "team_beta": 0,
      "team_gamma": 0
    },
    "total": 0
  },
  {
    "time": "04:13 AM",
    "timestamp": 1766376798842,
    "teams": {
      "team_alpha": 0,
      "team_beta": 0,
      "team_gamma": 0
    },
    "total": 0
  },
  {
    "time": "04:51 AM",
    "timestamp": 1766379085719,
    "teams": {
      "team_alpha": 0,
      "team_beta": 0,
      "team_gamma": 0
    },
    "total": 0
  },
  {
    "time": "05:13 AM",
    "timestamp": 1766380407624,
    "teams": {
      "team_alpha": 0,
      "team_beta": 0,
      "team_gamma": 0
    },
    "total": 0
  },
  {
    "time": "05:38 AM",
    "timestamp": 1766381901905,
    "teams": {
      "team_alpha": 0,
      "team_beta": 0,
      "team_gamma": 0
    },
    "total": 0
  },
  {
    "time": "05:50 AM",
    "timestamp": 1766382623103,
    "teams": {
      "team_alpha": 0,
      "team_beta": 0,
      "team_gamma": 0
    },
    "total": 0
  },
  {
    "time": "05:56 AM",
    "timestamp": 1766382980659,
    "teams": {
      "team_alpha": 0,
      "team_beta": 0,
      "team_gamma": 0
    },
    "total": 0
  },
  {
    "time": "06:21 AM",
    "timestamp": 1766384518357,
    "teams": {
      "team_alpha": 0,
      "team_beta": 0,
      "team_gamma": 0
    },
    "total": 0
  },
  {
    "time": "06:52 AM",
    "timestamp": 1766386377445,
    "teams": {
      "team_alpha": 0,
      "team_beta": 0,
      "team_gamma": 0
    },
    "total": 0
  },
  {
    "time": "07:13 AM",
    "timestamp": 1766387625201,
    "teams": {
      "team_alpha": 0,
      "team_beta": 0,
      "team_gamma": 0
    },
    "total": 0
  },
  {
    "time": "07:34 AM",
    "timestamp": 1766388862114,
    "teams": {
      "team_alpha": 0,
      "team_beta": 0,
      "team_gamma": 0
    },
    "total": 0
  },
  {
    "time": "07:46 AM",
    "timestamp": 1766389567233,
    "teams": {
      "team_alpha": 0,
      "team_beta": 0,
      "team_gamma": 0
    },
    "total": 0
  },
  {
    "time": "07:53 AM",
    "timestamp": 1766389986538,
    "teams": {
      "team_alpha": 0,
      "team_beta": 0,
      "team_gamma": 0
    },
    "total": 0
  },
  {
    "time": "07:58 AM",
    "timestamp": 1766390337417,
    "teams": {
      "team_alpha": 0,
      "team_beta": 0,
      "team_gamma": 0
    },
    "total": 0
  }
]